mf_manifest_tools_simple/__init__.py
mf_manifest_tools_simple/__main__.py
mf_manifest_tools_simple/aggregator.py
mf_manifest_tools_simple/data_struct.py
mf_manifest_tools_simple/exceptions.py
mf_manifest_tools_simple/generators/__init__.py
mf_manifest_tools_simple/generators/excel/__init__.py
mf_manifest_tools_simple/generators/excel/excel_worker.py
mf_manifest_tools_simple/generators/excel/template.xlsx
mf_manifest_tools_simple/generators/huawei_ap/__init__.py
mf_manifest_tools_simple/generators/huawei_ap/cmake.py
mf_manifest_tools_simple/generators/huawei_ap/cmake.template
mf_manifest_tools_simple/generators/huawei_ap/cmake_conan.template
mf_manifest_tools_simple/generators/huawei_ap/common.py
mf_manifest_tools_simple/generators/huawei_ap/conanfile.template
mf_manifest_tools_simple/generators/huawei_ap/exec.py
mf_manifest_tools_simple/generators/huawei_ap/main.template
mf_manifest_tools_simple/generators/huawei_ap/mdc_build.template
mf_manifest_tools_simple/generators/huawei_ap/service_instance.py
mf_manifest_tools_simple/generators/huawei_ap/service_interface.py
mf_manifest_tools_simple/generators/huawei_ap/swc.py
mf_manifest_tools_simple/generators/huawei_ap/swc_datatypes.py
mf_manifest_tools_simple/generators/mf_manifest/__init__.py
mf_manifest_tools_simple/generators/mfr/__init__.py
mf_manifest_tools_simple/generators/mfr/connections.py
mf_manifest_tools_simple/hackers/__init__.py
mf_manifest_tools_simple/hackers/huawei_camera.py
mf_manifest_tools_simple/hackers/huawei_datatype.py
mf_manifest_tools_simple/parser/__init__.py
mf_manifest_tools_simple/parser/manifest.schema.json
mf_manifest_tools_simple/parser/xml_parser.py
mf_manifest_tools_simple/parser/yaml_parser.py
mf_manifest_tools_simple/plot.py
mf_manifest_tools_simple/scanner.py
mf_manifest_tools_simple/searcher/__init__.py
mf_manifest_tools_simple/validator.py
mf_manifest_tools_simple-0.7.10.dist-info/entry_points.txt
mf_manifest_tools_simple-0.7.10.dist-info/WHEEL
mf_manifest_tools_simple-0.7.10.dist-info/METADATA
mf_manifest_tools_simple-0.7.10.dist-info/RECORD
