Metadata-Version: 2.1
Name: mf-manifest-tools-simple
Version: 0.7.10
Summary: MF Manifest Tools Simple
Author: xx
Requires-Python: >=3.6
Classifier: Programming Language :: Python :: 3
Classifier: Programming Language :: Python :: 3.10
Classifier: Programming Language :: Python :: 3.6
Classifier: Programming Language :: Python :: 3.7
Classifier: Programming Language :: Python :: 3.8
Classifier: Programming Language :: Python :: 3.9
Requires-Dist: PyPDF2 (>=1.26.0)
Requires-Dist: dataclasses (>=0.8,<0.9); python_version < "3.7"
Requires-Dist: docopt (>=0.6.2)
Requires-Dist: graphviz (>=0.16)
Requires-Dist: inflection (>=0.5.1)
Requires-Dist: jsonschema (>=3.2.0)
Requires-Dist: loguru (>=0.5.3)
Requires-Dist: lxml (>=4.6.3)
Requires-Dist: openpyxl (>=3.0.7)
Requires-Dist: pyyaml (>=5.4.1)
